Metadata-Version: 2.1
Name: magnifai-aut-sdk
Version: 0.0.3
Summary: Aut magnifai SDK
Home-page: https://github.com/magnifai-gbx/aut-sdk-python
Author: alejandro.rm
Author-email: alejandro.rm@globant.com
Classifier: Intended Audience :: Developers
Classifier: License :: OSI Approved :: MIT License
Classifier: Programming Language :: Python :: 3
Classifier: Operating System :: OS Independent
Requires-Python: >=3.9
Requires-Dist: iniconfig ==2.0.0
Requires-Dist: jsonpath ==0.82.2
Requires-Dist: pytest ==7.4.1
Requires-Dist: requests ==2.31.0
Requires-Dist: urllib3 ==2.0.4
